smashup/__init__.py
smashup/__main__.py
smashup/classes.py
smashup/cli.py
smashup/config.py
smashup/randomizer.py
smashup_cli-0.0.1.dist-info/licenses/LICENSE
smashup_cli-0.0.1.dist-info/METADATA
smashup_cli-0.0.1.dist-info/WHEEL
smashup_cli-0.0.1.dist-info/entry_points.txt
smashup_cli-0.0.1.dist-info/top_level.txt
smashup_cli-0.0.1.dist-info/RECORD
