Metadata-Version: 2.4
Name: smashup-cli
Version: 0.0.1
Summary: Smash Up faction randomizer with TUI configuration.
Author: Andrew Peng
License-Expression: MIT
Project-URL: Homepage, https://github.com/Andrew-peng/smashup-cli
Project-URL: Issues, https://github.com/Andrew-peng/smashup-cli/issues
Classifier: Programming Language :: Python :: 3
Classifier: Programming Language :: Python :: 3 :: Only
Classifier: Operating System :: OS Independent
Classifier: Environment :: Console
Classifier: Topic :: Games/Entertainment
Requires-Python: >=3.9
License-File: LICENSE
Requires-Dist: click
Requires-Dist: prompt_toolkit
Requires-Dist: rich
Requires-Dist: tomli; python_version < "3.11"
Provides-Extra: dev
Requires-Dist: pytest; extra == "dev"
Dynamic: license-file
